Workbook

Sheet 01_概要
B2: 沖縄県恩納村エリア ホテル競合料金調査 ／ 再構築フレームワーク
B3: 楽天トラベル週間実勢料金（対象週 × 各室タイプ）の採取 → 想定施設への再構築
B5: ■ 想定施設（対象物件 / Subject Property）
B6: 敷地面積 | C6: 1 ヘクタール（10,000 ㎡）
B7: 客室数 | C7: 150 室
B8: 宿泊形態 | C8: ホテル客室 ＋ コンドミニアム
B9: Spa | C9: 1 施設（想定）
B10: レストラン | C10: 3 ヶ所程度
B11: プール | C11: あり（屋外／必要に応じ屋内）
B12: 密度メモ | C12: 150室/1ha は高密度。ヴィラ主体リゾートより中層・都市型リゾート寄りの与件
B14: ■ 本ブックの構成
B15: 02_競合セット | C15: 恩納村エリアの実在競合ホテル（約20軒）と属性。採用理由・競合度を整理
B16: 03_料金採取テンプレ | C16: 楽天トラベル実勢料金の採取シート。行=競合／列=対象週×室タイプ。黄色セルに入力
B17: 04_再構築分析 | C17: 採取データを室タイプ別に集計し、想定150室プロダクトを価格ポジショニング
B18: 05_採取手順・定義 | C18: 採取ルール（採取単位・対象週・室タイプ定義）。採取の再現性を担保
B20: ■ 重要な前提・データ取扱い注意
B21: ・ 本ブックの料金欄（黄色セル）は空欄です。楽天トラベルの実勢料金は運用者側で採取のうえ入力してください。
B22: （動的な空室・料金ページのため自動採取はしていません。架空値は投資判断を誤らせるため未記入としています）
B23: ・ 競合の室数・属性は公開情報ベースの整理値です。最終確定前に各社公式で要確認（「要確認」表記の項目は特に）。
B24: ・ 採取の一貫性（1泊2名・素泊まり・税サ込 等）は「05_採取手順・定義」に従うこと。基準が揃わないと比較が崩れます。
B25: ・ 分析シートの平均/中央値は入力に応じて自動計算されます（空欄時は「—」表示、エラーは出ません）。

Sheet 02_競合セット
A1: 恩納村エリア 競合セット（実在ホテル・公開情報ベース／確定前に要検証）
A2: # | B2: ホテル名 | C2: ティア | D2: 客室数(概算) | E2: 主要施設 | F2: 立地/ビーチ | G2: 競合度 | H2: 備考
A3: 1 | B3: ハレクラニ沖縄 | C3: ラグジュアリー | D3: 360 | E3: 全室OV・5プール・スパハレクラニ・温泉 | F3: 名嘉真/ビーチ | G3: 直接 | H3: フォーブス5つ星常連。上限ベンチ
A4: 2 | B4: ハイアットリージェンシー瀬良垣アイランド沖縄 | C4: アッパーアップスケール | D4: 343（要確認） | E4: 島立地・複数レストラン・プール・スパ | F4: 瀬良垣島 | G4: 直接 | H4: 国際ブランド・大型
A5: 3 | B5: ANAインターコンチネンタル万座ビーチリゾート | C5: アッパーアップスケール | D5: 400（要確認） | E5: 万座ビーチ・マリーナ・プール・スパ | F5: 万座 | G5: 直接 | H5: 老舗大型リゾート
A6: 4 | B6: シェラトン沖縄サンマリーナリゾート | C6: アップスケール | D6: 300（要確認） | E6: プライベートビーチ・プール・スパ | F6: 冨着 | G6: 直接 | H6: 国際ブランド
A7: 5 | B7: ルネッサンス リゾート オキナワ | C7: アップスケール | D7: 377（要確認） | E7: 全室バルコニー・イルカ・タラソ・温泉 | F7: 山田/ビーチ | G7: 直接 | H7: ファミリー強い
A8: 6 | B8: ホテルモントレ沖縄 スパ＆リゾート | C8: アップスケール | D8: 339（要確認） | E8: 造波プール・天然温泉・プール4ヶ所 | F8: タイガービーチ | G8: 直接 | H8: スパ・温泉訴求
A9: 7 | B9: 沖縄かりゆしビーチリゾート・オーシャンスパ | C9: アップスケール | D9: 516 | E9: 6レストラン・オーシャンスパ・プール | F9: かりゆし | G9: 二次 | H9: 大型・多層価格
A10: 8 | B10: リザンシーパークホテル谷茶ベイ | C10: ミッドスケール〜アップスケール | D10: 県内最大級/約700 | E10: 800mビーチ・多数レストラン・プール | F10: 谷茶 | G10: 二次 | H10: 規模最大・価格レンジ広
A11: 9 | B11: ザ・ムーンビーチ ミュージアムリゾート | C11: アップスケール | D11: 255（要確認） | E11: 天然ムーンビーチ・プール・スパ | F11: 前兼久 | G11: 直接 | H11: 1975開業・改装継続
A12: 10 | B12: カフーリゾートフチャクコンド・ホテル | C12: アップスケール(コンド型) | D12: 333（要確認） | E12: ホテル/コンド/アネックス3棟・プール | F12: 冨着/ビーチ | G12: 直接★ | H12: コンド併設＝本件と近い
A13: 11 | B13: OKINAWA KARIYUSHI RESORT EXES ONNA | C13: ラグジュアリー | D13: 90 | E13: 全室59㎡+・スパ・高台OV・専用プール室 | F13: 名嘉真/高台 | G13: 直接 | H13: スパリゾート・受賞多数
A14: 12 | B14: HIYORIオーシャンリゾート沖縄 | C14: アッパーアップスケール | D14: 191（要確認） | E14: 全室スイート・ワイドテラス・プール | F14: 前兼久 | G14: 直接 | H14: 2021開業・新しめ
... A23: 21 | B23: （予備枠：20軒調整用） | C23: — | D23: — | E23: — | F23: — | G23: 予備 | H23: 20軒調整用の予備行
B25: ★＝コンドミニアム併設で本件（コンド併設150室）と特に構成が近い。「客室数(概算)」は公開情報からの整理値で、要確認表記は各社公式で確定のこと。

Sheet 03_料金採取テンプレ
A1: 楽天トラベル 実勢料金 採取シート（1泊2名・素泊まり・税サ込 基準／単位:円）
A2: 黄色セルに採取値を入力 ／ 対象週の実日付は下の行に記入 ／ 各室タイプの定義は「05_採取手順・定義」参照
A4: # | B4: ホテル名 | C4: W1 ピーク週 | G4: W2 ショルダー週 | K4: W3 オフ週 | O4: 楽天トラベルURL
C5: T1 | D5: T2 | E5: T3 | F5: T4 | G5: T1 | H5: T2 | I5: T3 | J5: T4 | K5: T1 | L5: T2 | M5: T3 | N5: T4
B6: 対象週の実日付→ | C6: 例:8/12〜 | G6: 例:8/12〜 | K6: 例:8/12〜
A7: 1 | B7: ハレクラニ沖縄 | O7: https://travel.rakuten.co.jp/HOTEL/172611/172611.html
A8: 2 | B8: ハイアットリージェンシー瀬良垣アイランド沖縄 | O8: https://travel.rakuten.co.jp/HOTEL/166320/166320.html
A9: 3 | B9: ANAインターコンチネンタル万座ビーチリゾート | O9: https://travel.rakuten.co.jp/HOTEL/16123/16123.html
A10: 4 | B10: シェラトン沖縄サンマリーナリゾート | O10: https://travel.rakuten.co.jp/HOTEL/13554/13554.html
A11: 5 | B11: ルネッサンス リゾート オキナワ | O11: https://travel.rakuten.co.jp/HOTEL/54315/54315.html
A12: 6 | B12: ホテルモントレ沖縄 スパ＆リゾート | O12: https://travel.rakuten.co.jp/HOTEL/141596/141596.html
A13: 7 | B13: 沖縄かりゆしビーチリゾート・オーシャンスパ | O13: https://travel.rakuten.co.jp/HOTEL/14275/14275.html
A14: 8 | B14: リザンシーパークホテル谷茶ベイ | O14: https://travel.rakuten.co.jp/HOTEL/52229/52229.html
A15: 9 | B15: ザ・ムーンビーチ ミュージアムリゾート | O15: https://travel.rakuten.co.jp/HOTEL/15483/15483.html
A16: 10 | B16: カフーリゾートフチャクコンド・ホテル | O16: https://travel.rakuten.co.jp/HOTEL/78239/78239.html
A17: 11 | B17: OKINAWA KARIYUSHI RESORT EXES ONNA | O17: https://travel.rakuten.co.jp/HOTEL/70318/70318.html
A18: 12 | B18: HIYORIオーシャンリゾート沖縄 | O18: https://travel.rakuten.co.jp/HOTEL/180687/180687.html
... A26: 20 | B26: オリエンタルヒルズ沖縄 | O26: https://travel.rakuten.co.jp/HOTEL/76791/76791.html
B28: 競合 平均 | C28: =IFERROR(AVERAGE(C7:C26),"—") | D28: =IFERROR(AVERAGE(D7:D26),"—") | E28: =IFERROR(AVERAGE(E7:E26),"—") | F28: =IFERROR(AVERAGE(F7:F26),"—") | G28: =IFERROR(AVERAGE(G7:G26),"—") | H28: =IFERROR(AVERAGE(H7:H26),"—") | I28: =IFERROR(AVERAGE(I7:I26),"—") | J28: =IFERROR(AVERAGE(J7:J26),"—") | ... N28: =IFERROR(AVERAGE(N7:N26),"—")
B29: 競合 中央値 | C29: =IFERROR(MEDIAN(C7:C26),"—") | D29: =IFERROR(MEDIAN(D7:D26),"—") | E29: =IFERROR(MEDIAN(E7:E26),"—") | F29: =IFERROR(MEDIAN(F7:F26),"—") | G29: =IFERROR(MEDIAN(G7:G26),"—") | H29: =IFERROR(MEDIAN(H7:H26),"—") | I29: =IFERROR(MEDIAN(I7:I26),"—") | J29: =IFERROR(MEDIAN(J7:J26),"—") | ... N29: =IFERROR(MEDIAN(N7:N26),"—")

Sheet 04_再構築分析
B2: 再構築分析：室タイプ別 競合レンジ vs 想定150室プロダクト
B4: A. 競合 実勢レンジ（採取シート「03」から自動集計・室タイプ別）
B5: 室タイプ | C5: ピーク(平均) | D5: ショルダー(平均) | E5: オフ(平均) | F5: 通期平均 | G5: 通期中央値
B6: T1 スタンダード | C6: =IFERROR(03_料金採取テンプレ!C28,"—") | D6: =IFERROR(03_料金採取テンプレ!G28,"—") | E6: =IFERROR(03_料金採取テンプレ!K28,"—") | F6: =IFERROR(AVERAGE(03_料金採取テンプレ!C7:C26,03_料金採取テンプレ!G7:G26,03_料金採取テンプレ!K7:K26),"—") | G6: =IFERROR(MEDIAN(03_料金採取テンプレ!C7:C26,03_料金採取テンプレ!G7:G26,03_料金採取テンプレ!K7:K26),"—")
B7: T2 デラックスOV | C7: =IFERROR(03_料金採取テンプレ!D28,"—") | D7: =IFERROR(03_料金採取テンプレ!H28,"—") | E7: =IFERROR(03_料金採取テンプレ!L28,"—") | F7: =IFERROR(AVERAGE(03_料金採取テンプレ!D7:D26,03_料金採取テンプレ!H7:H26,03_料金採取テンプレ!L7:L26),"—") | G7: =IFERROR(MEDIAN(03_料金採取テンプレ!D7:D26,03_料金採取テンプレ!H7:H26,03_料金採取テンプレ!L7:L26),"—")
B8: T3 スイート/プレミアム | C8: =IFERROR(03_料金採取テンプレ!E28,"—") | D8: =IFERROR(03_料金採取テンプレ!I28,"—") | E8: =IFERROR(03_料金採取テンプレ!M28,"—") | F8: =IFERROR(AVERAGE(03_料金採取テンプレ!E7:E26,03_料金採取テンプレ!I7:I26,03_料金採取テンプレ!M7:M26),"—") | G8: =IFERROR(MEDIAN(03_料金採取テンプレ!E7:E26,03_料金採取テンプレ!I7:I26,03_料金採取テンプレ!M7:M26),"—")
B9: T4 ヴィラ/コンド | C9: =IFERROR(03_料金採取テンプレ!F28,"—") | D9: =IFERROR(03_料金採取テンプレ!J28,"—") | E9: =IFERROR(03_料金採取テンプレ!N28,"—") | F9: =IFERROR(AVERAGE(03_料金採取テンプレ!F7:F26,03_料金採取テンプレ!J7:J26,03_料金採取テンプレ!N7:N26),"—") | G9: =IFERROR(MEDIAN(03_料金採取テンプレ!F7:F26,03_料金採取テンプレ!J7:J26,03_料金採取テンプレ!N7:N26),"—")
B12: B. 想定150室プロダクト：室構成（想定・編集可）と目標ADRの置き方
B13: 室タイプ | C13: 想定室数 | D13: 競合通期平均 | E13: 目標指数(%) | F13: 目標ADR(円) | G13: 月間潜在売上*
B14: T1 スタンダード | C14: 60 | D14: =IF(ISNUMBER(F6),F6,"—") | E14: 110 | F14: =IFERROR(D14*E14/100,"—") | G14: =IFERROR(C14*F14*30*0.7,"—")
B15: T2 デラックスOV | C15: 55 | D15: =IF(ISNUMBER(F7),F7,"—") | E15: 115 | F15: =IFERROR(D15*E15/100,"—") | G15: =IFERROR(C15*F15*30*0.7,"—")
B16: T3 スイート/プレミアム | C16: 25 | D16: =IF(ISNUMBER(F8),F8,"—") | E16: 120 | F16: =IFERROR(D16*E16/100,"—") | G16: =IFERROR(C16*F16*30*0.7,"—")
B17: T4 ヴィラ/コンド | C17: 10 | D17: =IF(ISNUMBER(F9),F9,"—") | E17: 130 | F17: =IFERROR(D17*E17/100,"—") | G17: =IFERROR(C17*F17*30*0.7,"—")
B18: 合計 / 加重 | C18: =SUM(C14:C17) | F18: =IFERROR(SUMPRODUCT(C14:C17,F14:F17)/C18,"—") | G18: =IFERROR(SUM(G14:G17),"—")
B20: * 月間潜在売上 = 室数 × 目標ADR × 30泊 × 稼働70%（稼働率は仮置き。事業計画で差替え）。
B21: 青字セル＝入力（室数・目標指数）。目標指数=競合通期平均に対する狙い(%)。100%=競合平均並み、120%=2割上。
B22: 「競合通期平均」はD列で室タイプ別に自動連動。採取シート03に実勢を入れると本表とパネルAが更新されます。

Sheet 05_採取手順・定義
B2: 採取手順・定義（採取の再現性を担保するルール）
B4: 採取媒体 | C4: 楽天トラベル（対象20軒それぞれの施設ページ空室・料金カレンダー）
B5: 採取単位 | C5: 1泊 / 2名1室 / 素泊まり（食事なし）を基準。朝食付しか無い場合は朝食付で採り、その旨を注記
B6: 料金定義 | C6: 税・サービス料込みの総額。ポイント還元前の提示価格。最安返金可プランを採用
B7: 対象週 W1 ピーク | C7: 例：8月お盆週（要:実日付をシート03に記入）。連休・繁忙を代表
B8: 対象週 W2 ショルダー | C8: 例：6月 または 10月の平常週。中間需要を代表
B9: 対象週 W3 オフ | C9: 例：12月の平日週。閑散を代表
B10: 採取曜日 | C10: 各対象週の平日(火or水)と週末(土)の2点を採り、必要に応じ平均。方式は全軒で統一
B11: 室タイプ T1 | C11: スタンダード（〜約35㎡ / 2名標準・ビュー指定なし）
B12: 室タイプ T2 | C12: デラックス／スーペリア・オーシャンビュー（約35〜55㎡）
B13: 室タイプ T3 | C13: スイート／プレミアム／クラブフロア（約55㎡〜）
B14: 室タイプ T4 | C14: ヴィラ／コンドミニアム／プール付・キッチン付等の特別形態
B15: マッピング | C15: 各社の実際の部屋名をT1〜T4のどれかに割当てて採取。判断に迷う部屋は備考へ
... B18: 更新頻度 | C18: 四半期ごと、または需要期前に再採取して時系列比較。列を複製して版管理
